krs/__init__.py
krs/apps.py
krs/bootstrap.py
krs/email.py
krs/groups.py
krs/institutions.py
krs/ldap.py
krs/py.typed
krs/rabbitmq.py
krs/token.py
krs/users.py
krs/util.py
wipac_keycloak_rest_services-1.5.1.dist-info/licenses/LICENSE
wipac_keycloak_rest_services-1.5.1.dist-info/METADATA
wipac_keycloak_rest_services-1.5.1.dist-info/WHEEL
wipac_keycloak_rest_services-1.5.1.dist-info/top_level.txt
wipac_keycloak_rest_services-1.5.1.dist-info/RECORD
