Metadata-Version: 2.4
Name: wipac-keycloak-rest-services
Version: 1.5.1
Summary: Services surrounding KeyCloak, that use the REST API to read/update state
Author-email: WIPAC Developers <developers@icecube.wisc.edu>
License-Expression: MIT
Project-URL: Homepage, https://pypi.org/project/wipac-keycloak-rest-services/
Project-URL: Tracker, https://github.com/WIPACrepo/keycloak-rest-services/issues
Project-URL: Source, https://github.com/WIPACrepo/keycloak-rest-services
Keywords: WIPAC,rest tools,utilities
Classifier: Programming Language :: Python :: 3.10
Classifier: Programming Language :: Python :: 3.11
Classifier: Programming Language :: Python :: 3.12
Classifier: Programming Language :: Python :: 3.13
Classifier: Programming Language :: Python :: 3.14
Requires-Python: <3.15,>=3.10
License-File: LICENSE
Requires-Dist: aio_pika
Requires-Dist: attrs
Requires-Dist: ldap3
Requires-Dist: motor
Requires-Dist: requests
Requires-Dist: unidecode
Requires-Dist: wipac-dev-tools
Requires-Dist: wipac-rest-tools
Provides-Extra: tests
Requires-Dist: coverage; extra == "tests"
Requires-Dist: flake8; extra == "tests"
Requires-Dist: pytest; extra == "tests"
Requires-Dist: pytest-asyncio; extra == "tests"
Requires-Dist: pytest-cov; extra == "tests"
Requires-Dist: pytest-mock; extra == "tests"
Provides-Extra: actions
Requires-Dist: asyncache; extra == "actions"
Requires-Dist: google-api-python-client; extra == "actions"
Requires-Dist: google-auth-oauthlib; extra == "actions"
Requires-Dist: jsonpath_ng; extra == "actions"
Provides-Extra: mypy
Requires-Dist: asyncache; extra == "mypy"
Requires-Dist: coverage; extra == "mypy"
Requires-Dist: flake8; extra == "mypy"
Requires-Dist: google-api-python-client; extra == "mypy"
Requires-Dist: google-auth-oauthlib; extra == "mypy"
Requires-Dist: jsonpath_ng; extra == "mypy"
Requires-Dist: pytest; extra == "mypy"
Requires-Dist: pytest-asyncio; extra == "mypy"
Requires-Dist: pytest-cov; extra == "mypy"
Requires-Dist: pytest-mock; extra == "mypy"
Dynamic: license-file
